[
    {
        "nurse1": "CT_18",
        "nurse2": "CT_31",
        "cooperation_score": 0.7188879389108221
    },
    {
        "nurse1": "CT_31",
        "nurse2": "TR_38",
        "cooperation_score": 0.9827689108800295
    },
    {
        "nurse1": "CT_27",
        "nurse2": "CT_31",
        "cooperation_score": 0.9180751251336121
    },
    {
        "nurse1": "CT_31",
        "nurse2": "NU_9",
        "cooperation_score": 1.314932594924855
    },
    {
        "nurse1": "CT_31",
        "nurse2": "HN_2",
        "cooperation_score": 1.3277817942291625
    },
    {
        "nurse1": "CT_31",
        "nurse2": "NU_17",
        "cooperation_score": 1.4342468017542054
    },
    {
        "nurse1": "CT_22",
        "nurse2": "CT_31",
        "cooperation_score": 0.9591687079690174
    },
    {
        "nurse1": "CT_31",
        "nurse2": "NU_16",
        "cooperation_score": 0.9581757537791323
    },
    {
        "nurse1": "CT_26",
        "nurse2": "CT_31",
        "cooperation_score": 0.813787863323467
    },
    {
        "nurse1": "CT_31",
        "nurse2": "TR_35",
        "cooperation_score": 0.5207641887359884
    },
    {
        "nurse1": "CT_24",
        "nurse2": "CT_31",
        "cooperation_score": 0.8805488199451048
    },
    {
        "nurse1": "CT_31",
        "nurse2": "NU_7",
        "cooperation_score": 1.171443524655599
    },
    {
        "nurse1": "CT_31",
        "nurse2": "NU_12",
        "cooperation_score": 1.1232866978223015
    },
    {
        "nurse1": "CT_31",
        "nurse2": "NU_15",
        "cooperation_score": 1.444016156066903
    },
    {
        "nurse1": "CT_31",
        "nurse2": "NU_14",
        "cooperation_score": 1.5033970959044993
    },
    {
        "nurse1": "CT_31",
        "nurse2": "TR_39",
        "cooperation_score": 1.0944987445138878
    },
    {
        "nurse1": "CT_31",
        "nurse2": "HN_3",
        "cooperation_score": 1.4702922320720813
    },
    {
        "nurse1": "CT_31",
        "nurse2": "NU_10",
        "cooperation_score": 1.0661507036658469
    },
    {
        "nurse1": "CT_30",
        "nurse2": "CT_31",
        "cooperation_score": 0.6889752189674789
    },
    {
        "nurse1": "CT_23",
        "nurse2": "CT_31",
        "cooperation_score": 1.0408616351492244
    },
    {
        "nurse1": "CT_31",
        "nurse2": "NU_6",
        "cooperation_score": 1.3075314133750666
    },
    {
        "nurse1": "CT_21",
        "nurse2": "CT_31",
        "cooperation_score": 0.5947004433997973
    },
    {
        "nurse1": "CT_19",
        "nurse2": "CT_31",
        "cooperation_score": 0.9639436400036749
    },
    {
        "nurse1": "CT_31",
        "nurse2": "HN_4",
        "cooperation_score": 1.3513122670243414
    },
    {
        "nurse1": "CT_31",
        "nurse2": "NU_11",
        "cooperation_score": 0.9411513179466471
    },
    {
        "nurse1": "CT_31",
        "nurse2": "NU_13",
        "cooperation_score": 1.142575667590811
    },
    {
        "nurse1": "CT_31",
        "nurse2": "HN_0",
        "cooperation_score": 1.2481736959291139
    },
    {
        "nurse1": "CT_28",
        "nurse2": "CT_31",
        "cooperation_score": 0.9384251397560723
    },
    {
        "nurse1": "CT_31",
        "nurse2": "NU_8",
        "cooperation_score": 1.3909846115879902
    },
    {
        "nurse1": "CT_20",
        "nurse2": "CT_31",
        "cooperation_score": 1.0057120624996516
    },
    {
        "nurse1": "CT_31",
        "nurse2": "TR_32",
        "cooperation_score": 1.040343134901622
    },
    {
        "nurse1": "CT_29",
        "nurse2": "CT_31",
        "cooperation_score": 1.0366053236409272
    },
    {
        "nurse1": "CT_31",
        "nurse2": "TR_33",
        "cooperation_score": 1.0117310005619333
    },
    {
        "nurse1": "CT_31",
        "nurse2": "TR_37",
        "cooperation_score": 0.9073353961663289
    },
    {
        "nurse1": "CT_25",
        "nurse2": "CT_31",
        "cooperation_score": 0.5872292911766596
    },
    {
        "nurse1": "CT_31",
        "nurse2": "TR_36",
        "cooperation_score": 0.5556127051483088
    },
    {
        "nurse1": "CT_31",
        "nurse2": "HN_5",
        "cooperation_score": 1.4884386640191594
    },
    {
        "nurse1": "CT_31",
        "nurse2": "TR_34",
        "cooperation_score": 0.875474304901213
    },
    {
        "nurse1": "CT_31",
        "nurse2": "HN_1",
        "cooperation_score": 1.1806594119674616
    },
    {
        "nurse1": "CT_18",
        "nurse2": "TR_38",
        "cooperation_score": 1.0832670238781423
    },
    {
        "nurse1": "CT_18",
        "nurse2": "CT_27",
        "cooperation_score": 0.523741418764302
    },
    {
        "nurse1": "CT_18",
        "nurse2": "NU_9",
        "cooperation_score": 0.7955738705738705
    },
    {
        "nurse1": "CT_18",
        "nurse2": "HN_2",
        "cooperation_score": 1.0808168139050491
    },
    {
        "nurse1": "CT_18",
        "nurse2": "NU_17",
        "cooperation_score": 0.906741386632691
    },
    {
        "nurse1": "CT_18",
        "nurse2": "CT_22",
        "cooperation_score": 0.5868125725323867
    },
    {
        "nurse1": "CT_18",
        "nurse2": "NU_16",
        "cooperation_score": 0.9827029250942294
    },
    {
        "nurse1": "CT_18",
        "nurse2": "CT_26",
        "cooperation_score": 0.7617112849310992
    },
    {
        "nurse1": "CT_18",
        "nurse2": "TR_35",
        "cooperation_score": 0.6406009910805307
    },
    {
        "nurse1": "CT_18",
        "nurse2": "CT_24",
        "cooperation_score": 0.8463863750628458
    },
    {
        "nurse1": "CT_18",
        "nurse2": "NU_7",
        "cooperation_score": 1.0646098182862889
    },
    {
        "nurse1": "CT_18",
        "nurse2": "NU_12",
        "cooperation_score": 1.2141935249133393
    },
    {
        "nurse1": "CT_18",
        "nurse2": "NU_15",
        "cooperation_score": 1.031776847387966
    },
    {
        "nurse1": "CT_18",
        "nurse2": "NU_14",
        "cooperation_score": 1.1360032195709946
    },
    {
        "nurse1": "CT_18",
        "nurse2": "TR_39",
        "cooperation_score": 1.057964183443723
    },
    {
        "nurse1": "CT_18",
        "nurse2": "HN_3",
        "cooperation_score": 0.9787017362246195
    },
    {
        "nurse1": "CT_18",
        "nurse2": "NU_10",
        "cooperation_score": 0.8796955953067139
    },
    {
        "nurse1": "CT_18",
        "nurse2": "CT_30",
        "cooperation_score": 0.6297637003519356
    },
    {
        "nurse1": "CT_18",
        "nurse2": "CT_23",
        "cooperation_score": 1.0165346764182408
    },
    {
        "nurse1": "CT_18",
        "nurse2": "NU_6",
        "cooperation_score": 1.1479560042640538
    },
    {
        "nurse1": "CT_18",
        "nurse2": "CT_21",
        "cooperation_score": 0.898964849444389
    },
    {
        "nurse1": "CT_18",
        "nurse2": "CT_19",
        "cooperation_score": 0.884538018105793
    },
    {
        "nurse1": "CT_18",
        "nurse2": "HN_4",
        "cooperation_score": 1.059258225434696
    },
    {
        "nurse1": "CT_18",
        "nurse2": "NU_11",
        "cooperation_score": 0.8468207517120561
    },
    {
        "nurse1": "CT_18",
        "nurse2": "NU_13",
        "cooperation_score": 0.6572749603860789
    },
    {
        "nurse1": "CT_18",
        "nurse2": "HN_0",
        "cooperation_score": 0.9220727372043162
    },
    {
        "nurse1": "CT_18",
        "nurse2": "CT_28",
        "cooperation_score": 0.9051724876953708
    },
    {
        "nurse1": "CT_18",
        "nurse2": "NU_8",
        "cooperation_score": 1.225670045692929
    },
    {
        "nurse1": "CT_18",
        "nurse2": "CT_20",
        "cooperation_score": 1.0063879389108221
    },
    {
        "nurse1": "CT_18",
        "nurse2": "TR_32",
        "cooperation_score": 0.9436895262124095
    },
    {
        "nurse1": "CT_18",
        "nurse2": "CT_29",
        "cooperation_score": 0.6733211233211233
    },
    {
        "nurse1": "CT_18",
        "nurse2": "TR_33",
        "cooperation_score": 0.6379227053140096
    },
    {
        "nurse1": "CT_18",
        "nurse2": "TR_37",
        "cooperation_score": 0.7267643160596452
    },
    {
        "nurse1": "CT_18",
        "nurse2": "CT_25",
        "cooperation_score": 0.9271843352725706
    },
    {
        "nurse1": "CT_18",
        "nurse2": "TR_36",
        "cooperation_score": 0.8020830476712829
    },
    {
        "nurse1": "CT_18",
        "nurse2": "HN_5",
        "cooperation_score": 0.880284421460892
    },
    {
        "nurse1": "CT_18",
        "nurse2": "TR_34",
        "cooperation_score": 0.5329617735728922
    },
    {
        "nurse1": "CT_18",
        "nurse2": "HN_1",
        "cooperation_score": 1.3851868289948785
    },
    {
        "nurse1": "CT_27",
        "nurse2": "TR_38",
        "cooperation_score": 0.8638207838436671
    },
    {
        "nurse1": "NU_9",
        "nurse2": "TR_38",
        "cooperation_score": 1.1040366496248848
    },
    {
        "nurse1": "HN_2",
        "nurse2": "TR_38",
        "cooperation_score": 0.8768925518925519
    },
    {
        "nurse1": "NU_17",
        "nurse2": "TR_38",
        "cooperation_score": 1.0893744398539793
    },
    {
        "nurse1": "CT_22",
        "nurse2": "TR_38",
        "cooperation_score": 0.7511422787738576
    },
    {
        "nurse1": "NU_16",
        "nurse2": "TR_38",
        "cooperation_score": 1.3424574679370076
    },
    {
        "nurse1": "CT_26",
        "nurse2": "TR_38",
        "cooperation_score": 0.5442148924347067
    },
    {
        "nurse1": "TR_35",
        "nurse2": "TR_38",
        "cooperation_score": 0.4321382120295163
    },
    {
        "nurse1": "CT_24",
        "nurse2": "TR_38",
        "cooperation_score": 1.1261482798247504
    },
    {
        "nurse1": "NU_7",
        "nurse2": "TR_38",
        "cooperation_score": 0.7082606119370825
    },
    {
        "nurse1": "NU_12",
        "nurse2": "TR_38",
        "cooperation_score": 1.2421697153895297
    },
    {
        "nurse1": "NU_15",
        "nurse2": "TR_38",
        "cooperation_score": 1.256181609292728
    },
    {
        "nurse1": "NU_14",
        "nurse2": "TR_38",
        "cooperation_score": 1.0189434819230216
    },
    {
        "nurse1": "TR_38",
        "nurse2": "TR_39",
        "cooperation_score": 0.8973109477904875
    },
    {
        "nurse1": "HN_3",
        "nurse2": "TR_38",
        "cooperation_score": 1.2387157418268604
    },
    {
        "nurse1": "NU_10",
        "nurse2": "TR_38",
        "cooperation_score": 1.1041003572114758
    },
    {
        "nurse1": "CT_30",
        "nurse2": "TR_38",
        "cooperation_score": 0.6820396107160813
    },
    {
        "nurse1": "CT_23",
        "nurse2": "TR_38",
        "cooperation_score": 1.0103265871219163
    },
    {
        "nurse1": "NU_6",
        "nurse2": "TR_38",
        "cooperation_score": 1.2048681280879423
    },
    {
        "nurse1": "CT_21",
        "nurse2": "TR_38",
        "cooperation_score": 0.5036906791702188
    },
    {
        "nurse1": "CT_19",
        "nurse2": "TR_38",
        "cooperation_score": 0.8584849045526795
    },
    {
        "nurse1": "HN_4",
        "nurse2": "TR_38",
        "cooperation_score": 1.0470616801499153
    },
    {
        "nurse1": "NU_11",
        "nurse2": "TR_38",
        "cooperation_score": 0.9551540850453895
    },
    {
        "nurse1": "NU_13",
        "nurse2": "TR_38",
        "cooperation_score": 0.8183537508766342
    },
    {
        "nurse1": "HN_0",
        "nurse2": "TR_38",
        "cooperation_score": 0.8338803740119529
    },
    {
        "nurse1": "CT_28",
        "nurse2": "TR_38",
        "cooperation_score": 0.8925313706424891
    },
    {
        "nurse1": "NU_8",
        "nurse2": "TR_38",
        "cooperation_score": 1.596070478593362
    },
    {
        "nurse1": "CT_20",
        "nurse2": "TR_38",
        "cooperation_score": 1.1728482759593946
    },
    {
        "nurse1": "TR_32",
        "nurse2": "TR_38",
        "cooperation_score": 1.0248763948992783
    },
    {
        "nurse1": "CT_29",
        "nurse2": "TR_38",
        "cooperation_score": 0.6964303670186023
    },
    {
        "nurse1": "TR_33",
        "nurse2": "TR_38",
        "cooperation_score": 0.9332541712337108
    },
    {
        "nurse1": "TR_37",
        "nurse2": "TR_38",
        "cooperation_score": 0.37385709256418637
    },
    {
        "nurse1": "CT_25",
        "nurse2": "TR_38",
        "cooperation_score": 0.8984144940027293
    },
    {
        "nurse1": "TR_36",
        "nurse2": "TR_38",
        "cooperation_score": 0.4538687619569972
    },
    {
        "nurse1": "HN_5",
        "nurse2": "TR_38",
        "cooperation_score": 1.3693467480232187
    },
    {
        "nurse1": "TR_34",
        "nurse2": "TR_38",
        "cooperation_score": 0.6000252656363843
    },
    {
        "nurse1": "HN_1",
        "nurse2": "TR_38",
        "cooperation_score": 1.4126728233926373
    },
    {
        "nurse1": "CT_27",
        "nurse2": "NU_9",
        "cooperation_score": 1.0605601555830388
    },
    {
        "nurse1": "CT_27",
        "nurse2": "HN_2",
        "cooperation_score": 1.0445922498554077
    },
    {
        "nurse1": "CT_27",
        "nurse2": "NU_17",
        "cooperation_score": 0.7783042965469941
    },
    {
        "nurse1": "CT_22",
        "nurse2": "CT_27",
        "cooperation_score": 0.6640695546806734
    },
    {
        "nurse1": "CT_27",
        "nurse2": "NU_16",
        "cooperation_score": 1.5103648084988102
    },
    {
        "nurse1": "CT_26",
        "nurse2": "CT_27",
        "cooperation_score": 0.4991304017619807
    },
    {
        "nurse1": "CT_27",
        "nurse2": "TR_35",
        "cooperation_score": 1.0479879739470532
    },
    {
        "nurse1": "CT_24",
        "nurse2": "CT_27",
        "cooperation_score": 1.3501999877151314
    },
    {
        "nurse1": "CT_27",
        "nurse2": "NU_7",
        "cooperation_score": 0.9240544543176121
    },
    {
        "nurse1": "CT_27",
        "nurse2": "NU_12",
        "cooperation_score": 1.2410568217995193
    },
    {
        "nurse1": "CT_27",
        "nurse2": "NU_15",
        "cooperation_score": 1.246187684453265
    },
    {
        "nurse1": "CT_27",
        "nurse2": "NU_14",
        "cooperation_score": 1.147561428304126
    },
    {
        "nurse1": "CT_27",
        "nurse2": "TR_39",
        "cooperation_score": 0.8891074854461583
    },
    {
        "nurse1": "CT_27",
        "nurse2": "HN_3",
        "cooperation_score": 1.002172635175058
    },
    {
        "nurse1": "CT_27",
        "nurse2": "NU_10",
        "cooperation_score": 1.3404232734256962
    },
    {
        "nurse1": "CT_27",
        "nurse2": "CT_30",
        "cooperation_score": 0.32990748931151404
    },
    {
        "nurse1": "CT_23",
        "nurse2": "CT_27",
        "cooperation_score": 0.686023112818442
    },
    {
        "nurse1": "CT_27",
        "nurse2": "NU_6",
        "cooperation_score": 1.4044691834316954
    },
    {
        "nurse1": "CT_21",
        "nurse2": "CT_27",
        "cooperation_score": 0.45840251640493934
    },
    {
        "nurse1": "CT_19",
        "nurse2": "CT_27",
        "cooperation_score": 0.8555203108911549
    },
    {
        "nurse1": "CT_27",
        "nurse2": "HN_4",
        "cooperation_score": 1.4486288249597576
    },
    {
        "nurse1": "CT_27",
        "nurse2": "NU_11",
        "cooperation_score": 1.1465505826489808
    },
    {
        "nurse1": "CT_27",
        "nurse2": "NU_13",
        "cooperation_score": 0.9685640797634336
    },
    {
        "nurse1": "CT_27",
        "nurse2": "HN_0",
        "cooperation_score": 1.2047023867608737
    },
    {
        "nurse1": "CT_27",
        "nurse2": "CT_28",
        "cooperation_score": 0.5771138203565178
    },
    {
        "nurse1": "CT_27",
        "nurse2": "NU_8",
        "cooperation_score": 1.44081218190284
    },
    {
        "nurse1": "CT_20",
        "nurse2": "CT_27",
        "cooperation_score": 0.734896447310635
    },
    {
        "nurse1": "CT_27",
        "nurse2": "TR_32",
        "cooperation_score": 0.9461184268611242
    },
    {
        "nurse1": "CT_27",
        "nurse2": "CT_29",
        "cooperation_score": 0.7992967844512466
    },
    {
        "nurse1": "CT_27",
        "nurse2": "TR_33",
        "cooperation_score": 0.9772160128500147
    },
    {
        "nurse1": "CT_27",
        "nurse2": "TR_37",
        "cooperation_score": 0.8789878235463106
    },
    {
        "nurse1": "CT_25",
        "nurse2": "CT_27",
        "cooperation_score": 1.3748360542629623
    },
    {
        "nurse1": "CT_27",
        "nurse2": "TR_36",
        "cooperation_score": 0.447078169732632
    },
    {
        "nurse1": "CT_27",
        "nurse2": "HN_5",
        "cooperation_score": 1.2077402845356136
    },
    {
        "nurse1": "CT_27",
        "nurse2": "TR_34",
        "cooperation_score": 0.6362242861384737
    },
    {
        "nurse1": "CT_27",
        "nurse2": "HN_1",
        "cooperation_score": 1.4255006818087312
    },
    {
        "nurse1": "HN_2",
        "nurse2": "NU_9",
        "cooperation_score": 1.7947375723691514
    },
    {
        "nurse1": "NU_17",
        "nurse2": "NU_9",
        "cooperation_score": 1.3704071642152138
    },
    {
        "nurse1": "CT_22",
        "nurse2": "NU_9",
        "cooperation_score": 0.753370166349706
    },
    {
        "nurse1": "NU_16",
        "nurse2": "NU_9",
        "cooperation_score": 1.454798270409389
    },
    {
        "nurse1": "CT_26",
        "nurse2": "NU_9",
        "cooperation_score": 0.7953754578754578
    },
    {
        "nurse1": "NU_9",
        "nurse2": "TR_35",
        "cooperation_score": 0.8736082615878014
    },
    {
        "nurse1": "CT_24",
        "nurse2": "NU_9",
        "cooperation_score": 1.5070298838252127
    },
    {
        "nurse1": "NU_7",
        "nurse2": "NU_9",
        "cooperation_score": 1.943401816621631
    },
    {
        "nurse1": "NU_12",
        "nurse2": "NU_9",
        "cooperation_score": 1.420350773461892
    },
    {
        "nurse1": "NU_15",
        "nurse2": "NU_9",
        "cooperation_score": 1.6521541008534548
    },
    {
        "nurse1": "NU_14",
        "nurse2": "NU_9",
        "cooperation_score": 1.9284958892157036
    },
    {
        "nurse1": "NU_9",
        "nurse2": "TR_39",
        "cooperation_score": 1.0585950599108493
    },
    {
        "nurse1": "HN_3",
        "nurse2": "NU_9",
        "cooperation_score": 1.7245715956393703
    },
    {
        "nurse1": "NU_10",
        "nurse2": "NU_9",
        "cooperation_score": 1.405329318308858
    },
    {
        "nurse1": "CT_30",
        "nurse2": "NU_9",
        "cooperation_score": 0.9610124954165202
    },
    {
        "nurse1": "CT_23",
        "nurse2": "NU_9",
        "cooperation_score": 0.9148559773559773
    },
    {
        "nurse1": "NU_6",
        "nurse2": "NU_9",
        "cooperation_score": 1.4526198932310117
    },
    {
        "nurse1": "CT_21",
        "nurse2": "NU_9",
        "cooperation_score": 0.8791675715588759
    },
    {
        "nurse1": "CT_19",
        "nurse2": "NU_9",
        "cooperation_score": 1.7080020540698289
    },
    {
        "nurse1": "HN_4",
        "nurse2": "NU_9",
        "cooperation_score": 1.9509673790784978
    },
    {
        "nurse1": "NU_11",
        "nurse2": "NU_9",
        "cooperation_score": 1.3742557135510427
    },
    {
        "nurse1": "NU_13",
        "nurse2": "NU_9",
        "cooperation_score": 1.0293914418914418
    },
    {
        "nurse1": "HN_0",
        "nurse2": "NU_9",
        "cooperation_score": 1.3273082166035457
    },
    {
        "nurse1": "CT_28",
        "nurse2": "NU_9",
        "cooperation_score": 0.8188638545836688
    },
    {
        "nurse1": "NU_8",
        "nurse2": "NU_9",
        "cooperation_score": 1.4947523952319348
    },
    {
        "nurse1": "CT_20",
        "nurse2": "NU_9",
        "cooperation_score": 1.4037951498629246
    },
    {
        "nurse1": "NU_9",
        "nurse2": "TR_32",
        "cooperation_score": 1.6019456850339204
    },
    {
        "nurse1": "CT_29",
        "nurse2": "NU_9",
        "cooperation_score": 1.0089038870150056
    },
    {
        "nurse1": "NU_9",
        "nurse2": "TR_33",
        "cooperation_score": 1.5105924762035947
    },
    {
        "nurse1": "NU_9",
        "nurse2": "TR_37",
        "cooperation_score": 0.8798052824368614
    },
    {
        "nurse1": "CT_25",
        "nurse2": "NU_9",
        "cooperation_score": 1.2066770503841442
    },
    {
        "nurse1": "NU_9",
        "nurse2": "TR_36",
        "cooperation_score": 0.9486151561380395
    },
    {
        "nurse1": "HN_5",
        "nurse2": "NU_9",
        "cooperation_score": 1.9502870351705996
    },
    {
        "nurse1": "NU_9",
        "nurse2": "TR_34",
        "cooperation_score": 0.626386039365579
    },
    {
        "nurse1": "HN_1",
        "nurse2": "NU_9",
        "cooperation_score": 1.9944666444666446
    },
    {
        "nurse1": "HN_2",
        "nurse2": "NU_17",
        "cooperation_score": 1.9359439537071117
    },
    {
        "nurse1": "CT_22",
        "nurse2": "HN_2",
        "cooperation_score": 1.0062899518781871
    },
    {
        "nurse1": "HN_2",
        "nurse2": "NU_16",
        "cooperation_score": 1.7629586057217637
    },
    {
        "nurse1": "CT_26",
        "nurse2": "HN_2",
        "cooperation_score": 0.9492521367521368
    },
    {
        "nurse1": "HN_2",
        "nurse2": "TR_35",
        "cooperation_score": 0.8772204103086456
    },
    {
        "nurse1": "CT_24",
        "nurse2": "HN_2",
        "cooperation_score": 1.4563092308448344
    },
    {
        "nurse1": "HN_2",
        "nurse2": "NU_7",
        "cooperation_score": 1.8401373909887844
    },
    {
        "nurse1": "HN_2",
        "nurse2": "NU_12",
        "cooperation_score": 1.838892029023608
    },
    {
        "nurse1": "HN_2",
        "nurse2": "NU_15",
        "cooperation_score": 1.6264774398288329
    },
    {
        "nurse1": "HN_2",
        "nurse2": "NU_14",
        "cooperation_score": 1.7849134482648414
    },
    {
        "nurse1": "HN_2",
        "nurse2": "TR_39",
        "cooperation_score": 1.5308301347775033
    },
    {
        "nurse1": "HN_2",
        "nurse2": "HN_3",
        "cooperation_score": 1.9536838161838161
    },
    {
        "nurse1": "HN_2",
        "nurse2": "NU_10",
        "cooperation_score": 1.8564384145266497
    },
    {
        "nurse1": "CT_30",
        "nurse2": "HN_2",
        "cooperation_score": 0.7690235203393098
    },
    {
        "nurse1": "CT_23",
        "nurse2": "HN_2",
        "cooperation_score": 1.1424315880198233
    },
    {
        "nurse1": "HN_2",
        "nurse2": "NU_6",
        "cooperation_score": 1.6340171223685154
    },
    {
        "nurse1": "CT_21",
        "nurse2": "HN_2",
        "cooperation_score": 1.0110074136389926
    },
    {
        "nurse1": "CT_19",
        "nurse2": "HN_2",
        "cooperation_score": 1.1587014292896645
    },
    {
        "nurse1": "HN_2",
        "nurse2": "HN_4",
        "cooperation_score": 2.2466295099809033
    },
    {
        "nurse1": "HN_2",
        "nurse2": "NU_11",
        "cooperation_score": 1.5815845704003597
    },
    {
        "nurse1": "HN_2",
        "nurse2": "NU_13",
        "cooperation_score": 1.387751545839781
    },
    {
        "nurse1": "HN_0",
        "nurse2": "HN_2",
        "cooperation_score": 1.8838868003341687
    },
    {
        "nurse1": "CT_28",
        "nurse2": "HN_2",
        "cooperation_score": 0.8545152946468736
    },
    {
        "nurse1": "HN_2",
        "nurse2": "NU_8",
        "cooperation_score": 1.2452228327228325
    },
    {
        "nurse1": "CT_20",
        "nurse2": "HN_2",
        "cooperation_score": 1.0382381507381506
    },
    {
        "nurse1": "HN_2",
        "nurse2": "TR_32",
        "cooperation_score": 1.3561178587494376
    },
    {
        "nurse1": "CT_29",
        "nurse2": "HN_2",
        "cooperation_score": 1.3445367497999077
    },
    {
        "nurse1": "HN_2",
        "nurse2": "TR_33",
        "cooperation_score": 1.3635538438170016
    },
    {
        "nurse1": "HN_2",
        "nurse2": "TR_37",
        "cooperation_score": 1.3557051565565499
    },
    {
        "nurse1": "CT_25",
        "nurse2": "HN_2",
        "cooperation_score": 1.3662488826962509
    },
    {
        "nurse1": "HN_2",
        "nurse2": "TR_36",
        "cooperation_score": 0.9275592828224406
    },
    {
        "nurse1": "HN_2",
        "nurse2": "HN_5",
        "cooperation_score": 1.362498509402534
    },
    {
        "nurse1": "HN_2",
        "nurse2": "TR_34",
        "cooperation_score": 0.8455451411333764
    },
    {
        "nurse1": "HN_1",
        "nurse2": "HN_2",
        "cooperation_score": 1.5810568516450871
    },
    {
        "nurse1": "CT_22",
        "nurse2": "NU_17",
        "cooperation_score": 0.7622388834076141
    },
    {
        "nurse1": "NU_16",
        "nurse2": "NU_17",
        "cooperation_score": 1.5641442735634417
    },
    {
        "nurse1": "CT_26",
        "nurse2": "NU_17",
        "cooperation_score": 0.9360923991728946
    },
    {
        "nurse1": "NU_17",
        "nurse2": "TR_35",
        "cooperation_score": 1.2285266876749579
    },
    {
        "nurse1": "CT_24",
        "nurse2": "NU_17",
        "cooperation_score": 1.5516290254293348
    },
    {
        "nurse1": "NU_17",
        "nurse2": "NU_7",
        "cooperation_score": 1.5987508363669356
    },
    {
        "nurse1": "NU_12",
        "nurse2": "NU_17",
        "cooperation_score": 1.963532911017431
    },
    {
        "nurse1": "NU_15",
        "nurse2": "NU_17",
        "cooperation_score": 1.7761030449262378
    },
    {
        "nurse1": "NU_14",
        "nurse2": "NU_17",
        "cooperation_score": 1.7923021236253163
    },
    {
        "nurse1": "NU_17",
        "nurse2": "TR_39",
        "cooperation_score": 1.490279249698418
    },
    {
        "nurse1": "HN_3",
        "nurse2": "NU_17",
        "cooperation_score": 2.119996737233243
    },
    {
        "nurse1": "NU_10",
        "nurse2": "NU_17",
        "cooperation_score": 1.7920627431227782
    },
    {
        "nurse1": "CT_30",
        "nurse2": "NU_17",
        "cooperation_score": 0.8107594589792732
    },
    {
        "nurse1": "CT_23",
        "nurse2": "NU_17",
        "cooperation_score": 0.9629632478468122
    },
    {
        "nurse1": "NU_17",
        "nurse2": "NU_6",
        "cooperation_score": 1.7600468932512277
    },
    {
        "nurse1": "CT_21",
        "nurse2": "NU_17",
        "cooperation_score": 1.1610826722820262
    },
    {
        "nurse1": "CT_19",
        "nurse2": "NU_17",
        "cooperation_score": 1.3408667169267519
    },
    {
        "nurse1": "HN_4",
        "nurse2": "NU_17",
        "cooperation_score": 2.056216001920336
    },
    {
        "nurse1": "NU_11",
        "nurse2": "NU_17",
        "cooperation_score": 1.2169772893608537
    },
    {
        "nurse1": "NU_13",
        "nurse2": "NU_17",
        "cooperation_score": 1.2004840603676248
    },
    {
        "nurse1": "HN_0",
        "nurse2": "NU_17",
        "cooperation_score": 1.763566107954653
    },
    {
        "nurse1": "CT_28",
        "nurse2": "NU_17",
        "cooperation_score": 1.2025096062012202
    },
    {
        "nurse1": "NU_17",
        "nurse2": "NU_8",
        "cooperation_score": 1.8119442505042853
    },
    {
        "nurse1": "CT_20",
        "nurse2": "NU_17",
        "cooperation_score": 1.446728442060923
    },
    {
        "nurse1": "NU_17",
        "nurse2": "TR_32",
        "cooperation_score": 1.4862379693413479
    },
    {
        "nurse1": "CT_29",
        "nurse2": "NU_17",
        "cooperation_score": 1.2128973924252562
    },
    {
        "nurse1": "NU_17",
        "nurse2": "TR_33",
        "cooperation_score": 1.492569503304461
    },
    {
        "nurse1": "NU_17",
        "nurse2": "TR_37",
        "cooperation_score": 1.3056259944569275
    },
    {
        "nurse1": "CT_25",
        "nurse2": "NU_17",
        "cooperation_score": 0.9799966545322583
    },
    {
        "nurse1": "NU_17",
        "nurse2": "TR_36",
        "cooperation_score": 0.9157802122198406
    },
    {
        "nurse1": "HN_5",
        "nurse2": "NU_17",
        "cooperation_score": 1.4077581302426503
    },
    {
        "nurse1": "NU_17",
        "nurse2": "TR_34",
        "cooperation_score": 0.7794754937708228
    },
    {
        "nurse1": "HN_1",
        "nurse2": "NU_17",
        "cooperation_score": 1.59483694410165
    },
    {
        "nurse1": "CT_22",
        "nurse2": "NU_16",
        "cooperation_score": 1.0117538578216327
    },
    {
        "nurse1": "CT_22",
        "nurse2": "CT_26",
        "cooperation_score": 0.9155476231714621
    },
    {
        "nurse1": "CT_22",
        "nurse2": "TR_35",
        "cooperation_score": 0.8996777588260291
    },
    {
        "nurse1": "CT_22",
        "nurse2": "CT_24",
        "cooperation_score": 0.898738523482769
    },
    {
        "nurse1": "CT_22",
        "nurse2": "NU_7",
        "cooperation_score": 0.8752513826043238
    },
    {
        "nurse1": "CT_22",
        "nurse2": "NU_12",
        "cooperation_score": 1.0698253185246724
    },
    {
        "nurse1": "CT_22",
        "nurse2": "NU_15",
        "cooperation_score": 1.1154684610718397
    },
    {
        "nurse1": "CT_22",
        "nurse2": "NU_14",
        "cooperation_score": 0.9695990069442082
    },
    {
        "nurse1": "CT_22",
        "nurse2": "TR_39",
        "cooperation_score": 0.7797108722031323
    },
    {
        "nurse1": "CT_22",
        "nurse2": "HN_3",
        "cooperation_score": 1.0186438804237297
    },
    {
        "nurse1": "CT_22",
        "nurse2": "NU_10",
        "cooperation_score": 1.0041418791570227
    },
    {
        "nurse1": "CT_22",
        "nurse2": "CT_30",
        "cooperation_score": 0.4827921046961295
    },
    {
        "nurse1": "CT_22",
        "nurse2": "CT_23",
        "cooperation_score": 0.8552398152243355
    },
    {
        "nurse1": "CT_22",
        "nurse2": "NU_6",
        "cooperation_score": 1.2154628509269108
    },
    {
        "nurse1": "CT_21",
        "nurse2": "CT_22",
        "cooperation_score": 0.42642113498891
    },
    {
        "nurse1": "CT_19",
        "nurse2": "CT_22",
        "cooperation_score": 0.8823530084130434
    },
    {
        "nurse1": "CT_22",
        "nurse2": "HN_4",
        "cooperation_score": 1.132302590135071
    },
    {
        "nurse1": "CT_22",
        "nurse2": "NU_11",
        "cooperation_score": 0.7888906099583849
    },
    {
        "nurse1": "CT_22",
        "nurse2": "NU_13",
        "cooperation_score": 1.001355279567354
    },
    {
        "nurse1": "CT_22",
        "nurse2": "HN_0",
        "cooperation_score": 0.9342044034919927
    },
    {
        "nurse1": "CT_22",
        "nurse2": "CT_28",
        "cooperation_score": 0.7104148474504511
    },
    {
        "nurse1": "CT_22",
        "nurse2": "NU_8",
        "cooperation_score": 1.3360746522662663
    },
    {
        "nurse1": "CT_20",
        "nurse2": "CT_22",
        "cooperation_score": 0.9553582496458388
    },
    {
        "nurse1": "CT_22",
        "nurse2": "TR_32",
        "cooperation_score": 1.0965763167001559
    },
    {
        "nurse1": "CT_22",
        "nurse2": "CT_29",
        "cooperation_score": 0.5686965066760463
    },
    {
        "nurse1": "CT_22",
        "nurse2": "TR_33",
        "cooperation_score": 0.7624120017073308
    },
    {
        "nurse1": "CT_22",
        "nurse2": "TR_37",
        "cooperation_score": 0.7458316795004101
    },
    {
        "nurse1": "CT_22",
        "nurse2": "CT_25",
        "cooperation_score": 0.7231666280579323
    },
    {
        "nurse1": "CT_22",
        "nurse2": "TR_36",
        "cooperation_score": 0.5552654932450329
    },
    {
        "nurse1": "CT_22",
        "nurse2": "HN_5",
        "cooperation_score": 0.9639446194164192
    },
    {
        "nurse1": "CT_22",
        "nurse2": "TR_34",
        "cooperation_score": 0.794936786863695
    },
    {
        "nurse1": "CT_22",
        "nurse2": "HN_1",
        "cooperation_score": 1.026849741246026
    },
    {
        "nurse1": "CT_26",
        "nurse2": "NU_16",
        "cooperation_score": 1.0509373796138501
    },
    {
        "nurse1": "NU_16",
        "nurse2": "TR_35",
        "cooperation_score": 0.8619989629580422
    },
    {
        "nurse1": "CT_24",
        "nurse2": "NU_16",
        "cooperation_score": 1.836602882206261
    },
    {
        "nurse1": "NU_16",
        "nurse2": "NU_7",
        "cooperation_score": 1.4558651273047558
    },
    {
        "nurse1": "NU_12",
        "nurse2": "NU_16",
        "cooperation_score": 1.5824969606080792
    },
    {
        "nurse1": "NU_15",
        "nurse2": "NU_16",
        "cooperation_score": 1.4629653941876313
    },
    {
        "nurse1": "NU_14",
        "nurse2": "NU_16",
        "cooperation_score": 1.7946536334845662
    },
    {
        "nurse1": "NU_16",
        "nurse2": "TR_39",
        "cooperation_score": 1.405142267657411
    },
    {
        "nurse1": "HN_3",
        "nurse2": "NU_16",
        "cooperation_score": 1.4645125441480942
    },
    {
        "nurse1": "NU_10",
        "nurse2": "NU_16",
        "cooperation_score": 1.6129012469485615
    },
    {
        "nurse1": "CT_30",
        "nurse2": "NU_16",
        "cooperation_score": 0.6187676487599088
    },
    {
        "nurse1": "CT_23",
        "nurse2": "NU_16",
        "cooperation_score": 1.1525935736613486
    },
    {
        "nurse1": "NU_16",
        "nurse2": "NU_6",
        "cooperation_score": 1.8123775762085088
    },
    {
        "nurse1": "CT_21",
        "nurse2": "NU_16",
        "cooperation_score": 1.1164647156436092
    },
    {
        "nurse1": "CT_19",
        "nurse2": "NU_16",
        "cooperation_score": 1.142947589494904
    },
    {
        "nurse1": "HN_4",
        "nurse2": "NU_16",
        "cooperation_score": 1.8517174030483357
    },
    {
        "nurse1": "NU_11",
        "nurse2": "NU_16",
        "cooperation_score": 1.2671244532228514
    },
    {
        "nurse1": "NU_13",
        "nurse2": "NU_16",
        "cooperation_score": 0.9202453663131412
    },
    {
        "nurse1": "HN_0",
        "nurse2": "NU_16",
        "cooperation_score": 1.7266980811249892
    },
    {
        "nurse1": "CT_28",
        "nurse2": "NU_16",
        "cooperation_score": 0.9772724465600358
    },
    {
        "nurse1": "NU_16",
        "nurse2": "NU_8",
        "cooperation_score": 1.6524580953289392
    },
    {
        "nurse1": "CT_20",
        "nurse2": "NU_16",
        "cooperation_score": 1.5209237799710944
    },
    {
        "nurse1": "NU_16",
        "nurse2": "TR_32",
        "cooperation_score": 1.058161165684049
    },
    {
        "nurse1": "CT_29",
        "nurse2": "NU_16",
        "cooperation_score": 1.1980696619005948
    },
    {
        "nurse1": "NU_16",
        "nurse2": "TR_33",
        "cooperation_score": 1.0968186324526343
    },
    {
        "nurse1": "NU_16",
        "nurse2": "TR_37",
        "cooperation_score": 1.323275012105945
    },
    {
        "nurse1": "CT_25",
        "nurse2": "NU_16",
        "cooperation_score": 1.4166438379825108
    },
    {
        "nurse1": "NU_16",
        "nurse2": "TR_36",
        "cooperation_score": 0.8154255086682062
    },
    {
        "nurse1": "HN_5",
        "nurse2": "NU_16",
        "cooperation_score": 1.6095010237963532
    },
    {
        "nurse1": "NU_16",
        "nurse2": "TR_34",
        "cooperation_score": 0.8231179909888349
    },
    {
        "nurse1": "HN_1",
        "nurse2": "NU_16",
        "cooperation_score": 1.7839640751405457
    },
    {
        "nurse1": "CT_26",
        "nurse2": "TR_35",
        "cooperation_score": 0.8066117491040092
    },
    {
        "nurse1": "CT_24",
        "nurse2": "CT_26",
        "cooperation_score": 0.9742145109792169
    },
    {
        "nurse1": "CT_26",
        "nurse2": "NU_7",
        "cooperation_score": 0.9073619191266249
    },
    {
        "nurse1": "CT_26",
        "nurse2": "NU_12",
        "cooperation_score": 1.1627499521462368
    },
    {
        "nurse1": "CT_26",
        "nurse2": "NU_15",
        "cooperation_score": 1.0922760418116457
    },
    {
        "nurse1": "CT_26",
        "nurse2": "NU_14",
        "cooperation_score": 1.103110103690599
    },
    {
        "nurse1": "CT_26",
        "nurse2": "TR_39",
        "cooperation_score": 1.0357566238371192
    },
    {
        "nurse1": "CT_26",
        "nurse2": "HN_3",
        "cooperation_score": 1.2352963385084128
    },
    {
        "nurse1": "CT_26",
        "nurse2": "NU_10",
        "cooperation_score": 1.3107857184095573
    },
    {
        "nurse1": "CT_26",
        "nurse2": "CT_30",
        "cooperation_score": 0.8164612133652381
    },
    {
        "nurse1": "CT_23",
        "nurse2": "CT_26",
        "cooperation_score": 0.9307856745937242
    },
    {
        "nurse1": "CT_26",
        "nurse2": "NU_6",
        "cooperation_score": 0.9272770916733766
    },
    {
        "nurse1": "CT_21",
        "nurse2": "CT_26",
        "cooperation_score": 0.885392222156928
    },
    {
        "nurse1": "CT_19",
        "nurse2": "CT_26",
        "cooperation_score": 1.0097197522120123
    },
    {
        "nurse1": "CT_26",
        "nurse2": "HN_4",
        "cooperation_score": 1.2556761049408107
    },
    {
        "nurse1": "CT_26",
        "nurse2": "NU_11",
        "cooperation_score": 0.9136492592374945
    },
    {
        "nurse1": "CT_26",
        "nurse2": "NU_13",
        "cooperation_score": 0.8996422866778904
    },
    {
        "nurse1": "CT_26",
        "nurse2": "HN_0",
        "cooperation_score": 1.323803767611817
    },
    {
        "nurse1": "CT_26",
        "nurse2": "CT_28",
        "cooperation_score": 0.7063013139251528
    },
    {
        "nurse1": "CT_26",
        "nurse2": "NU_8",
        "cooperation_score": 1.124754674290278
    },
    {
        "nurse1": "CT_20",
        "nurse2": "CT_26",
        "cooperation_score": 0.8156498300461149
    },
    {
        "nurse1": "CT_26",
        "nurse2": "TR_32",
        "cooperation_score": 0.8735281230637268
    },
    {
        "nurse1": "CT_26",
        "nurse2": "CT_29",
        "cooperation_score": 0.628684632361103
    },
    {
        "nurse1": "CT_26",
        "nurse2": "TR_33",
        "cooperation_score": 0.5196950710108604
    },
    {
        "nurse1": "CT_26",
        "nurse2": "TR_37",
        "cooperation_score": 0.9556016480939081
    },
    {
        "nurse1": "CT_25",
        "nurse2": "CT_26",
        "cooperation_score": 0.7952579283461636
    },
    {
        "nurse1": "CT_26",
        "nurse2": "TR_36",
        "cooperation_score": 0.7349325511090217
    },
    {
        "nurse1": "CT_26",
        "nurse2": "HN_5",
        "cooperation_score": 1.093951778355803
    },
    {
        "nurse1": "CT_26",
        "nurse2": "TR_34",
        "cooperation_score": 0.661682615629984
    },
    {
        "nurse1": "CT_26",
        "nurse2": "HN_1",
        "cooperation_score": 1.233340064648114
    },
    {
        "nurse1": "CT_24",
        "nurse2": "TR_35",
        "cooperation_score": 1.0148460270902726
    },
    {
        "nurse1": "NU_7",
        "nurse2": "TR_35",
        "cooperation_score": 0.5336134453781513
    },
    {
        "nurse1": "NU_12",
        "nurse2": "TR_35",
        "cooperation_score": 0.8823673946116402
    },
    {
        "nurse1": "NU_15",
        "nurse2": "TR_35",
        "cooperation_score": 1.5250871604502645
    },
    {
        "nurse1": "NU_14",
        "nurse2": "TR_35",
        "cooperation_score": 1.1815084281566985
    },
    {
        "nurse1": "TR_35",
        "nurse2": "TR_39",
        "cooperation_score": 0.8502703851539496
    },
    {
        "nurse1": "HN_3",
        "nurse2": "TR_35",
        "cooperation_score": 1.4245537885933632
    },
    {
        "nurse1": "NU_10",
        "nurse2": "TR_35",
        "cooperation_score": 1.5764760493391534
    },
    {
        "nurse1": "CT_30",
        "nurse2": "TR_35",
        "cooperation_score": 0.4114245833286081
    },
    {
        "nurse1": "CT_23",
        "nurse2": "TR_35",
        "cooperation_score": 0.6574400129118125
    },
    {
        "nurse1": "NU_6",
        "nurse2": "TR_35",
        "cooperation_score": 1.3039969905059419
    },
    {
        "nurse1": "CT_21",
        "nurse2": "TR_35",
        "cooperation_score": 0.7445747205337998
    },
    {
        "nurse1": "CT_19",
        "nurse2": "TR_35",
        "cooperation_score": 1.3410650551046297
    },
    {
        "nurse1": "HN_4",
        "nurse2": "TR_35",
        "cooperation_score": 1.4988923729013242
    },
    {
        "nurse1": "NU_11",
        "nurse2": "TR_35",
        "cooperation_score": 0.961337124796204
    },
    {
        "nurse1": "NU_13",
        "nurse2": "TR_35",
        "cooperation_score": 1.1120270924988922
    },
    {
        "nurse1": "HN_0",
        "nurse2": "TR_35",
        "cooperation_score": 1.242320350152831
    },
    {
        "nurse1": "CT_28",
        "nurse2": "TR_35",
        "cooperation_score": 0.6713021311856955
    },
    {
        "nurse1": "NU_8",
        "nurse2": "TR_35",
        "cooperation_score": 1.582513884053459
    },
    {
        "nurse1": "CT_20",
        "nurse2": "TR_35",
        "cooperation_score": 0.914839586386901
    },
    {
        "nurse1": "TR_32",
        "nurse2": "TR_35",
        "cooperation_score": 0.7981021285739283
    },
    {
        "nurse1": "CT_29",
        "nurse2": "TR_35",
        "cooperation_score": 0.8202758913436663
    },
    {
        "nurse1": "TR_33",
        "nurse2": "TR_35",
        "cooperation_score": 0.6356844879593567
    },
    {
        "nurse1": "TR_35",
        "nurse2": "TR_37",
        "cooperation_score": 0.860466664622675
    },
    {
        "nurse1": "CT_25",
        "nurse2": "TR_35",
        "cooperation_score": 0.8290139669935067
    },
    {
        "nurse1": "TR_35",
        "nurse2": "TR_36",
        "cooperation_score": 0.4669028754706504
    },
    {
        "nurse1": "HN_5",
        "nurse2": "TR_35",
        "cooperation_score": 1.0254446390046739
    },
    {
        "nurse1": "TR_34",
        "nurse2": "TR_35",
        "cooperation_score": 0.5850749667616002
    },
    {
        "nurse1": "HN_1",
        "nurse2": "TR_35",
        "cooperation_score": 1.3594425998837765
    },
    {
        "nurse1": "CT_24",
        "nurse2": "NU_7",
        "cooperation_score": 1.4365722684608135
    },
    {
        "nurse1": "CT_24",
        "nurse2": "NU_12",
        "cooperation_score": 1.4811357616075613
    },
    {
        "nurse1": "CT_24",
        "nurse2": "NU_15",
        "cooperation_score": 1.5479031015947153
    },
    {
        "nurse1": "CT_24",
        "nurse2": "NU_14",
        "cooperation_score": 1.6246425315310764
    },
    {
        "nurse1": "CT_24",
        "nurse2": "TR_39",
        "cooperation_score": 1.154118774242613
    },
    {
        "nurse1": "CT_24",
        "nurse2": "HN_3",
        "cooperation_score": 1.4342058339500796
    },
    {
        "nurse1": "CT_24",
        "nurse2": "NU_10",
        "cooperation_score": 1.3647489019931474
    },
    {
        "nurse1": "CT_24",
        "nurse2": "CT_30",
        "cooperation_score": 0.7477987483792439
    },
    {
        "nurse1": "CT_23",
        "nurse2": "CT_24",
        "cooperation_score": 0.9862861811391224
    },
    {
        "nurse1": "CT_24",
        "nurse2": "NU_6",
        "cooperation_score": 1.4358502851301342
    },
    {
        "nurse1": "CT_21",
        "nurse2": "CT_24",
        "cooperation_score": 0.9456055023930915
    },
    {
        "nurse1": "CT_19",
        "nurse2": "CT_24",
        "cooperation_score": 1.2017452389894845
    },
    {
        "nurse1": "CT_24",
        "nurse2": "HN_4",
        "cooperation_score": 1.9652334020132511
    },
    {
        "nurse1": "CT_24",
        "nurse2": "NU_11",
        "cooperation_score": 1.4355005359800757
    },
    {
        "nurse1": "CT_24",
        "nurse2": "NU_13",
        "cooperation_score": 1.3913463986993402
    },
    {
        "nurse1": "CT_24",
        "nurse2": "HN_0",
        "cooperation_score": 1.2047459534453073
    },
    {
        "nurse1": "CT_24",
        "nurse2": "CT_28",
        "cooperation_score": 1.0092303723108675
    },
    {
        "nurse1": "CT_24",
        "nurse2": "NU_8",
        "cooperation_score": 1.7339376380936482
    },
    {
        "nurse1": "CT_20",
        "nurse2": "CT_24",
        "cooperation_score": 1.280986422642433
    },
    {
        "nurse1": "CT_24",
        "nurse2": "TR_32",
        "cooperation_score": 1.2604740417820914
    },
    {
        "nurse1": "CT_24",
        "nurse2": "CT_29",
        "cooperation_score": 1.0872976123127556
    },
    {
        "nurse1": "CT_24",
        "nurse2": "TR_33",
        "cooperation_score": 0.9701494826646258
    },
    {
        "nurse1": "CT_24",
        "nurse2": "TR_37",
        "cooperation_score": 1.0285118648121745
    },
    {
        "nurse1": "CT_24",
        "nurse2": "CT_25",
        "cooperation_score": 1.2417117654111192
    },
    {
        "nurse1": "CT_24",
        "nurse2": "TR_36",
        "cooperation_score": 0.8002634046903128
    },
    {
        "nurse1": "CT_24",
        "nurse2": "HN_5",
        "cooperation_score": 1.3455814466414817
    },
    {
        "nurse1": "CT_24",
        "nurse2": "TR_34",
        "cooperation_score": 0.6783442119119869
    },
    {
        "nurse1": "CT_24",
        "nurse2": "HN_1",
        "cooperation_score": 1.763418770771712
    },
    {
        "nurse1": "NU_12",
        "nurse2": "NU_7",
        "cooperation_score": 1.4703572141652637
    },
    {
        "nurse1": "NU_15",
        "nurse2": "NU_7",
        "cooperation_score": 1.6215970261248898
    },
    {
        "nurse1": "NU_14",
        "nurse2": "NU_7",
        "cooperation_score": 1.673605556809891
    },
    {
        "nurse1": "NU_7",
        "nurse2": "TR_39",
        "cooperation_score": 1.417414220626295
    },
    {
        "nurse1": "HN_3",
        "nurse2": "NU_7",
        "cooperation_score": 1.4123545572074983
    },
    {
        "nurse1": "NU_10",
        "nurse2": "NU_7",
        "cooperation_score": 1.5116048983696042
    },
    {
        "nurse1": "CT_30",
        "nurse2": "NU_7",
        "cooperation_score": 0.8729343154265755
    },
    {
        "nurse1": "CT_23",
        "nurse2": "NU_7",
        "cooperation_score": 1.1670401493930904
    },
    {
        "nurse1": "NU_6",
        "nurse2": "NU_7",
        "cooperation_score": 1.3263912515073506
    },
    {
        "nurse1": "CT_21",
        "nurse2": "NU_7",
        "cooperation_score": 1.3582790145870642
    },
    {
        "nurse1": "CT_19",
        "nurse2": "NU_7",
        "cooperation_score": 1.2257453330982742
    },
    {
        "nurse1": "HN_4",
        "nurse2": "NU_7",
        "cooperation_score": 1.7351214102375092
    },
    {
        "nurse1": "NU_11",
        "nurse2": "NU_7",
        "cooperation_score": 1.2871266590306838
    },
    {
        "nurse1": "NU_13",
        "nurse2": "NU_7",
        "cooperation_score": 1.3422765959530665
    },
    {
        "nurse1": "HN_0",
        "nurse2": "NU_7",
        "cooperation_score": 1.359882455006294
    },
    {
        "nurse1": "CT_28",
        "nurse2": "NU_7",
        "cooperation_score": 0.8174309737390233
    },
    {
        "nurse1": "NU_7",
        "nurse2": "NU_8",
        "cooperation_score": 1.0689499226263932
    },
    {
        "nurse1": "CT_20",
        "nurse2": "NU_7",
        "cooperation_score": 0.8965463458110516
    },
    {
        "nurse1": "NU_7",
        "nurse2": "TR_32",
        "cooperation_score": 1.2679481036679179
    },
    {
        "nurse1": "CT_29",
        "nurse2": "NU_7",
        "cooperation_score": 0.8513626853023138
    },
    {
        "nurse1": "NU_7",
        "nurse2": "TR_33",
        "cooperation_score": 1.2974957189353475
    },
    {
        "nurse1": "NU_7",
        "nurse2": "TR_37",
        "cooperation_score": 1.5145915316193954
    },
    {
        "nurse1": "CT_25",
        "nurse2": "NU_7",
        "cooperation_score": 0.9830033700389739
    },
    {
        "nurse1": "NU_7",
        "nurse2": "TR_36",
        "cooperation_score": 1.105132526572155
    },
    {
        "nurse1": "HN_5",
        "nurse2": "NU_7",
        "cooperation_score": 1.6011693973381282
    },
    {
        "nurse1": "NU_7",
        "nurse2": "TR_34",
        "cooperation_score": 0.6648082309847014
    },
    {
        "nurse1": "HN_1",
        "nurse2": "NU_7",
        "cooperation_score": 1.6905079397726457
    },
    {
        "nurse1": "NU_12",
        "nurse2": "NU_15",
        "cooperation_score": 1.4746306009615338
    },
    {
        "nurse1": "NU_12",
        "nurse2": "NU_14",
        "cooperation_score": 1.7382314151276999
    },
    {
        "nurse1": "NU_12",
        "nurse2": "TR_39",
        "cooperation_score": 1.5768831443754046
    },
    {
        "nurse1": "HN_3",
        "nurse2": "NU_12",
        "cooperation_score": 1.2656632224508115
    },
    {
        "nurse1": "NU_10",
        "nurse2": "NU_12",
        "cooperation_score": 1.4867875229868768
    },
    {
        "nurse1": "CT_30",
        "nurse2": "NU_12",
        "cooperation_score": 1.1673311767352015
    },
    {
        "nurse1": "CT_23",
        "nurse2": "NU_12",
        "cooperation_score": 1.1826242170282417
    },
    {
        "nurse1": "NU_12",
        "nurse2": "NU_6",
        "cooperation_score": 1.8133847389803774
    },
    {
        "nurse1": "CT_21",
        "nurse2": "NU_12",
        "cooperation_score": 1.2798205133882883
    },
    {
        "nurse1": "CT_19",
        "nurse2": "NU_12",
        "cooperation_score": 1.1868069909630012
    },
    {
        "nurse1": "HN_4",
        "nurse2": "NU_12",
        "cooperation_score": 1.928774539238599
    },
    {
        "nurse1": "NU_11",
        "nurse2": "NU_12",
        "cooperation_score": 1.43822548560905
    },
    {
        "nurse1": "NU_12",
        "nurse2": "NU_13",
        "cooperation_score": 1.433581081800896
    },
    {
        "nurse1": "HN_0",
        "nurse2": "NU_12",
        "cooperation_score": 1.5438127475043615
    },
    {
        "nurse1": "CT_28",
        "nurse2": "NU_12",
        "cooperation_score": 0.8093699558095842
    },
    {
        "nurse1": "NU_12",
        "nurse2": "NU_8",
        "cooperation_score": 2.1021739339615233
    },
    {
        "nurse1": "CT_20",
        "nurse2": "NU_12",
        "cooperation_score": 1.4569566512442405
    },
    {
        "nurse1": "NU_12",
        "nurse2": "TR_32",
        "cooperation_score": 1.6349263868226716
    },
    {
        "nurse1": "CT_29",
        "nurse2": "NU_12",
        "cooperation_score": 1.3790646902640442
    },
    {
        "nurse1": "NU_12",
        "nurse2": "TR_33",
        "cooperation_score": 0.9424245330356517
    },
    {
        "nurse1": "NU_12",
        "nurse2": "TR_37",
        "cooperation_score": 0.9030735776091813
    },
    {
        "nurse1": "CT_25",
        "nurse2": "NU_12",
        "cooperation_score": 1.3731461205296849
    },
    {
        "nurse1": "NU_12",
        "nurse2": "TR_36",
        "cooperation_score": 1.2153589515583056
    },
    {
        "nurse1": "HN_5",
        "nurse2": "NU_12",
        "cooperation_score": 1.4095906400624396
    },
    {
        "nurse1": "NU_12",
        "nurse2": "TR_34",
        "cooperation_score": 0.7141745966974801
    },
    {
        "nurse1": "HN_1",
        "nurse2": "NU_12",
        "cooperation_score": 1.8507674901637747
    },
    {
        "nurse1": "NU_14",
        "nurse2": "NU_15",
        "cooperation_score": 1.5723064330413905
    },
    {
        "nurse1": "NU_15",
        "nurse2": "TR_39",
        "cooperation_score": 1.1959325016751992
    },
    {
        "nurse1": "HN_3",
        "nurse2": "NU_15",
        "cooperation_score": 1.9495727625674455
    },
    {
        "nurse1": "NU_10",
        "nurse2": "NU_15",
        "cooperation_score": 1.9385425346254528
    },
    {
        "nurse1": "CT_30",
        "nurse2": "NU_15",
        "cooperation_score": 1.0274261256459398
    },
    {
        "nurse1": "CT_23",
        "nurse2": "NU_15",
        "cooperation_score": 1.5127310239303777
    },
    {
        "nurse1": "NU_15",
        "nurse2": "NU_6",
        "cooperation_score": 1.3677285547793019
    },
    {
        "nurse1": "CT_21",
        "nurse2": "NU_15",
        "cooperation_score": 1.2290887745911976
    },
    {
        "nurse1": "CT_19",
        "nurse2": "NU_15",
        "cooperation_score": 1.1384973613604654
    },
    {
        "nurse1": "HN_4",
        "nurse2": "NU_15",
        "cooperation_score": 2.3077936797128475
    },
    {
        "nurse1": "NU_11",
        "nurse2": "NU_15",
        "cooperation_score": 1.5764516456382789
    },
    {
        "nurse1": "NU_13",
        "nurse2": "NU_15",
        "cooperation_score": 1.8474892180925968
    },
    {
        "nurse1": "HN_0",
        "nurse2": "NU_15",
        "cooperation_score": 1.8539466065933288
    },
    {
        "nurse1": "CT_28",
        "nurse2": "NU_15",
        "cooperation_score": 1.2218027700377276
    },
    {
        "nurse1": "NU_15",
        "nurse2": "NU_8",
        "cooperation_score": 2.0471830770895245
    },
    {
        "nurse1": "CT_20",
        "nurse2": "NU_15",
        "cooperation_score": 1.3768487760276695
    },
    {
        "nurse1": "NU_15",
        "nurse2": "TR_32",
        "cooperation_score": 1.4177744454211676
    },
    {
        "nurse1": "CT_29",
        "nurse2": "NU_15",
        "cooperation_score": 1.1771776454203429
    },
    {
        "nurse1": "NU_15",
        "nurse2": "TR_33",
        "cooperation_score": 1.4672425497805763
    },
    {
        "nurse1": "NU_15",
        "nurse2": "TR_37",
        "cooperation_score": 1.2250213651680872
    },
    {
        "nurse1": "CT_25",
        "nurse2": "NU_15",
        "cooperation_score": 1.1918079712348795
    },
    {
        "nurse1": "NU_15",
        "nurse2": "TR_36",
        "cooperation_score": 0.8538047764592387
    },
    {
        "nurse1": "HN_5",
        "nurse2": "NU_15",
        "cooperation_score": 1.6523588797347042
    },
    {
        "nurse1": "NU_15",
        "nurse2": "TR_34",
        "cooperation_score": 1.1125926674991151
    },
    {
        "nurse1": "HN_1",
        "nurse2": "NU_15",
        "cooperation_score": 1.8660531848612343
    },
    {
        "nurse1": "NU_14",
        "nurse2": "TR_39",
        "cooperation_score": 1.4963953558145238
    },
    {
        "nurse1": "HN_3",
        "nurse2": "NU_14",
        "cooperation_score": 1.8610358451841154
    },
    {
        "nurse1": "NU_10",
        "nurse2": "NU_14",
        "cooperation_score": 1.5785268509104156
    },
    {
        "nurse1": "CT_30",
        "nurse2": "NU_14",
        "cooperation_score": 1.1039389102469597
    },
    {
        "nurse1": "CT_23",
        "nurse2": "NU_14",
        "cooperation_score": 1.7773056864539565
    },
    {
        "nurse1": "NU_14",
        "nurse2": "NU_6",
        "cooperation_score": 1.9360768273693971
    },
    {
        "nurse1": "CT_21",
        "nurse2": "NU_14",
        "cooperation_score": 1.2036974104849998
    },
    {
        "nurse1": "CT_19",
        "nurse2": "NU_14",
        "cooperation_score": 1.3334814551297254
    },
    {
        "nurse1": "HN_4",
        "nurse2": "NU_14",
        "cooperation_score": 2.4276782814708513
    },
    {
        "nurse1": "NU_11",
        "nurse2": "NU_14",
        "cooperation_score": 1.2795688644524288
    },
    {
        "nurse1": "NU_13",
        "nurse2": "NU_14",
        "cooperation_score": 1.3508424438142435
    },
    {
        "nurse1": "HN_0",
        "nurse2": "NU_14",
        "cooperation_score": 1.1736663018783762
    },
    {
        "nurse1": "CT_28",
        "nurse2": "NU_14",
        "cooperation_score": 0.9090823635092715
    },
    {
        "nurse1": "NU_14",
        "nurse2": "NU_8",
        "cooperation_score": 1.7855456491056843
    },
    {
        "nurse1": "CT_20",
        "nurse2": "NU_14",
        "cooperation_score": 1.4258512800072902
    },
    {
        "nurse1": "NU_14",
        "nurse2": "TR_32",
        "cooperation_score": 1.2611959362110796
    },
    {
        "nurse1": "CT_29",
        "nurse2": "NU_14",
        "cooperation_score": 1.1562657071171003
    },
    {
        "nurse1": "NU_14",
        "nurse2": "TR_33",
        "cooperation_score": 1.3388474084058954
    },
    {
        "nurse1": "NU_14",
        "nurse2": "TR_37",
        "cooperation_score": 1.05163635664376
    },
    {
        "nurse1": "CT_25",
        "nurse2": "NU_14",
        "cooperation_score": 1.4622061117417156
    },
    {
        "nurse1": "NU_14",
        "nurse2": "TR_36",
        "cooperation_score": 1.2655110369506652
    },
    {
        "nurse1": "HN_5",
        "nurse2": "NU_14",
        "cooperation_score": 1.9167699517544716
    },
    {
        "nurse1": "NU_14",
        "nurse2": "TR_34",
        "cooperation_score": 0.8815359333312625
    },
    {
        "nurse1": "HN_1",
        "nurse2": "NU_14",
        "cooperation_score": 2.0540642364171777
    },
    {
        "nurse1": "HN_3",
        "nurse2": "TR_39",
        "cooperation_score": 1.4299577729295725
    },
    {
        "nurse1": "NU_10",
        "nurse2": "TR_39",
        "cooperation_score": 1.5665152513988154
    },
    {
        "nurse1": "CT_30",
        "nurse2": "TR_39",
        "cooperation_score": 0.8302649534847677
    },
    {
        "nurse1": "CT_23",
        "nurse2": "TR_39",
        "cooperation_score": 1.1983740788458785
    },
    {
        "nurse1": "NU_6",
        "nurse2": "TR_39",
        "cooperation_score": 1.4149666681787423
    },
    {
        "nurse1": "CT_21",
        "nurse2": "TR_39",
        "cooperation_score": 1.1178457621333513
    },
    {
        "nurse1": "CT_19",
        "nurse2": "TR_39",
        "cooperation_score": 1.0102788407506404
    },
    {
        "nurse1": "HN_4",
        "nurse2": "TR_39",
        "cooperation_score": 1.3431773463894208
    },
    {
        "nurse1": "NU_11",
        "nurse2": "TR_39",
        "cooperation_score": 0.9430509104422148
    },
    {
        "nurse1": "NU_13",
        "nurse2": "TR_39",
        "cooperation_score": 1.4514798782752074
    },
    {
        "nurse1": "HN_0",
        "nurse2": "TR_39",
        "cooperation_score": 0.9128980067060561
    },
    {
        "nurse1": "CT_28",
        "nurse2": "TR_39",
        "cooperation_score": 0.830384204083558
    },
    {
        "nurse1": "NU_8",
        "nurse2": "TR_39",
        "cooperation_score": 1.3779339797293089
    },
    {
        "nurse1": "CT_20",
        "nurse2": "TR_39",
        "cooperation_score": 1.1517444228121976
    },
    {
        "nurse1": "TR_32",
        "nurse2": "TR_39",
        "cooperation_score": 0.9977863066249792
    },
    {
        "nurse1": "CT_29",
        "nurse2": "TR_39",
        "cooperation_score": 0.8081310201666239
    },
    {
        "nurse1": "TR_33",
        "nurse2": "TR_39",
        "cooperation_score": 1.160025353268051
    },
    {
        "nurse1": "TR_37",
        "nurse2": "TR_39",
        "cooperation_score": 0.8982001901270981
    },
    {
        "nurse1": "CT_25",
        "nurse2": "TR_39",
        "cooperation_score": 1.272166107885922
    },
    {
        "nurse1": "TR_36",
        "nurse2": "TR_39",
        "cooperation_score": 0.9867157524278266
    },
    {
        "nurse1": "HN_5",
        "nurse2": "TR_39",
        "cooperation_score": 1.3787363350443846
    },
    {
        "nurse1": "TR_34",
        "nurse2": "TR_39",
        "cooperation_score": 0.4683320620391559
    },
    {
        "nurse1": "HN_1",
        "nurse2": "TR_39",
        "cooperation_score": 1.520824845089551
    },
    {
        "nurse1": "HN_3",
        "nurse2": "NU_10",
        "cooperation_score": 1.9829421709368538
    },
    {
        "nurse1": "CT_30",
        "nurse2": "HN_3",
        "cooperation_score": 0.7558708233630833
    },
    {
        "nurse1": "CT_23",
        "nurse2": "HN_3",
        "cooperation_score": 1.500212006999596
    },
    {
        "nurse1": "HN_3",
        "nurse2": "NU_6",
        "cooperation_score": 1.618729029193089
    },
    {
        "nurse1": "CT_21",
        "nurse2": "HN_3",
        "cooperation_score": 1.0985211825684973
    },
    {
        "nurse1": "CT_19",
        "nurse2": "HN_3",
        "cooperation_score": 1.6462820603216348
    },
    {
        "nurse1": "HN_3",
        "nurse2": "HN_4",
        "cooperation_score": 1.7843602546927353
    },
    {
        "nurse1": "HN_3",
        "nurse2": "NU_11",
        "cooperation_score": 1.6263068772659566
    },
    {
        "nurse1": "HN_3",
        "nurse2": "NU_13",
        "cooperation_score": 1.6605396480547914
    },
    {
        "nurse1": "HN_0",
        "nurse2": "HN_3",
        "cooperation_score": 1.6835166108924355
    },
    {
        "nurse1": "CT_28",
        "nurse2": "HN_3",
        "cooperation_score": 1.2857190438224224
    },
    {
        "nurse1": "HN_3",
        "nurse2": "NU_8",
        "cooperation_score": 1.634189942772861
    },
    {
        "nurse1": "CT_20",
        "nurse2": "HN_3",
        "cooperation_score": 1.4135559414113055
    },
    {
        "nurse1": "HN_3",
        "nurse2": "TR_32",
        "cooperation_score": 1.2586568086719518
    },
    {
        "nurse1": "CT_29",
        "nurse2": "HN_3",
        "cooperation_score": 1.2028853570413673
    },
    {
        "nurse1": "HN_3",
        "nurse2": "TR_33",
        "cooperation_score": 1.3337003609752296
    },
    {
        "nurse1": "HN_3",
        "nurse2": "TR_37",
        "cooperation_score": 1.0796622351340348
    },
    {
        "nurse1": "CT_25",
        "nurse2": "HN_3",
        "cooperation_score": 1.109229176620481
    },
    {
        "nurse1": "HN_3",
        "nurse2": "TR_36",
        "cooperation_score": 0.5539824625502374
    },
    {
        "nurse1": "HN_3",
        "nurse2": "HN_5",
        "cooperation_score": 1.675755031226831
    },
    {
        "nurse1": "HN_3",
        "nurse2": "TR_34",
        "cooperation_score": 1.073058182376395
    },
    {
        "nurse1": "HN_1",
        "nurse2": "HN_3",
        "cooperation_score": 2.0383937527900375
    },
    {
        "nurse1": "CT_30",
        "nurse2": "NU_10",
        "cooperation_score": 0.944238991143016
    },
    {
        "nurse1": "CT_23",
        "nurse2": "NU_10",
        "cooperation_score": 1.0492639354632893
    },
    {
        "nurse1": "NU_10",
        "nurse2": "NU_6",
        "cooperation_score": 1.4374372817248708
    },
    {
        "nurse1": "CT_21",
        "nurse2": "NU_10",
        "cooperation_score": 0.948842674801754
    },
    {
        "nurse1": "CT_19",
        "nurse2": "NU_10",
        "cooperation_score": 1.270182343045447
    },
    {
        "nurse1": "HN_4",
        "nurse2": "NU_10",
        "cooperation_score": 1.8802441094001197
    },
    {
        "nurse1": "NU_10",
        "nurse2": "NU_11",
        "cooperation_score": 1.4894012991839078
    },
    {
        "nurse1": "NU_10",
        "nurse2": "NU_13",
        "cooperation_score": 1.9153824359858147
    },
    {
        "nurse1": "HN_0",
        "nurse2": "NU_10",
        "cooperation_score": 1.813949250148604
    },
    {
        "nurse1": "CT_28",
        "nurse2": "NU_10",
        "cooperation_score": 0.9835382997299138
    },
    {
        "nurse1": "NU_10",
        "nurse2": "NU_8",
        "cooperation_score": 1.7612782955965078
    },
    {
        "nurse1": "CT_20",
        "nurse2": "NU_10",
        "cooperation_score": 1.181748043426937
    },
    {
        "nurse1": "NU_10",
        "nurse2": "TR_32",
        "cooperation_score": 1.0177389846658926
    },
    {
        "nurse1": "CT_29",
        "nurse2": "NU_10",
        "cooperation_score": 0.7417044627722378
    },
    {
        "nurse1": "NU_10",
        "nurse2": "TR_33",
        "cooperation_score": 1.255897608172477
    },
    {
        "nurse1": "NU_10",
        "nurse2": "TR_37",
        "cooperation_score": 0.9485859584695229
    },
    {
        "nurse1": "CT_25",
        "nurse2": "NU_10",
        "cooperation_score": 1.2026001030796427
    },
    {
        "nurse1": "NU_10",
        "nurse2": "TR_36",
        "cooperation_score": 0.3766940646736043
    },
    {
        "nurse1": "HN_5",
        "nurse2": "NU_10",
        "cooperation_score": 1.704258472230272
    },
    {
        "nurse1": "NU_10",
        "nurse2": "TR_34",
        "cooperation_score": 1.1487037786102263
    },
    {
        "nurse1": "HN_1",
        "nurse2": "NU_10",
        "cooperation_score": 1.5501361770324618
    },
    {
        "nurse1": "CT_23",
        "nurse2": "CT_30",
        "cooperation_score": 0.8235906035828635
    },
    {
        "nurse1": "CT_30",
        "nurse2": "NU_6",
        "cooperation_score": 0.8213164888087489
    },
    {
        "nurse1": "CT_21",
        "nurse2": "CT_30",
        "cooperation_score": 0.7884956546721252
    },
    {
        "nurse1": "CT_19",
        "nurse2": "CT_30",
        "cooperation_score": 0.9928079058884012
    },
    {
        "nurse1": "CT_30",
        "nurse2": "HN_4",
        "cooperation_score": 1.243477660969921
    },
    {
        "nurse1": "CT_30",
        "nurse2": "NU_11",
        "cooperation_score": 0.7072039072039072
    },
    {
        "nurse1": "CT_30",
        "nurse2": "NU_13",
        "cooperation_score": 0.8385613354653603
    },
    {
        "nurse1": "CT_30",
        "nurse2": "HN_0",
        "cooperation_score": 0.8954975579975579
    },
    {
        "nurse1": "CT_28",
        "nurse2": "CT_30",
        "cooperation_score": 0.6972063454261597
    },
    {
        "nurse1": "CT_30",
        "nurse2": "NU_8",
        "cooperation_score": 1.0733446077486324
    },
    {
        "nurse1": "CT_20",
        "nurse2": "CT_30",
        "cooperation_score": 0.5640280471162824
    },
    {
        "nurse1": "CT_30",
        "nurse2": "TR_32",
        "cooperation_score": 0.9632085020242914
    },
    {
        "nurse1": "CT_29",
        "nurse2": "CT_30",
        "cooperation_score": 0.8030454624494872
    },
    {
        "nurse1": "CT_30",
        "nurse2": "TR_33",
        "cooperation_score": 0.8295018277216419
    },
    {
        "nurse1": "CT_30",
        "nurse2": "TR_37",
        "cooperation_score": 0.564477086381111
    },
    {
        "nurse1": "CT_25",
        "nurse2": "CT_30",
        "cooperation_score": 0.5732160813043166
    },
    {
        "nurse1": "CT_30",
        "nurse2": "TR_36",
        "cooperation_score": 0.6454905173945422
    },
    {
        "nurse1": "CT_30",
        "nurse2": "HN_5",
        "cooperation_score": 1.1014969078049575
    },
    {
        "nurse1": "CT_30",
        "nurse2": "TR_34",
        "cooperation_score": 0.4731004075044322
    },
    {
        "nurse1": "CT_30",
        "nurse2": "HN_1",
        "cooperation_score": 0.9502020038784744
    },
    {
        "nurse1": "CT_23",
        "nurse2": "NU_6",
        "cooperation_score": 0.8875288711976019
    },
    {
        "nurse1": "CT_21",
        "nurse2": "CT_23",
        "cooperation_score": 0.946475100631111
    },
    {
        "nurse1": "CT_19",
        "nurse2": "CT_23",
        "cooperation_score": 0.8905309415909766
    },
    {
        "nurse1": "CT_23",
        "nurse2": "HN_4",
        "cooperation_score": 1.3828271401800811
    },
    {
        "nurse1": "CT_23",
        "nurse2": "NU_11",
        "cooperation_score": 1.0350838774751818
    },
    {
        "nurse1": "CT_23",
        "nurse2": "NU_13",
        "cooperation_score": 1.012910419698009
    },
    {
        "nurse1": "CT_23",
        "nurse2": "HN_0",
        "cooperation_score": 0.9901028495068742
    },
    {
        "nurse1": "CT_23",
        "nurse2": "CT_28",
        "cooperation_score": 0.5984379640490827
    },
    {
        "nurse1": "CT_23",
        "nurse2": "NU_8",
        "cooperation_score": 1.143571017270371
    },
    {
        "nurse1": "CT_20",
        "nurse2": "CT_23",
        "cooperation_score": 1.0202472220425511
    },
    {
        "nurse1": "CT_23",
        "nurse2": "TR_32",
        "cooperation_score": 0.8747695572924407
    },
    {
        "nurse1": "CT_23",
        "nurse2": "CT_29",
        "cooperation_score": 0.5187881562881563
    },
    {
        "nurse1": "CT_23",
        "nurse2": "TR_33",
        "cooperation_score": 0.9401897794851086
    },
    {
        "nurse1": "CT_23",
        "nurse2": "TR_37",
        "cooperation_score": 0.8389964681524784
    },
    {
        "nurse1": "CT_23",
        "nurse2": "CT_25",
        "cooperation_score": 1.0752307333189686
    },
    {
        "nurse1": "CT_23",
        "nurse2": "TR_36",
        "cooperation_score": 0.8224450386215092
    },
    {
        "nurse1": "CT_23",
        "nurse2": "HN_5",
        "cooperation_score": 1.183182808763304
    },
    {
        "nurse1": "CT_23",
        "nurse2": "TR_34",
        "cooperation_score": 0.8529404060515247
    },
    {
        "nurse1": "CT_23",
        "nurse2": "HN_1",
        "cooperation_score": 1.4182578644265948
    },
    {
        "nurse1": "CT_21",
        "nurse2": "NU_6",
        "cooperation_score": 1.0558438751314643
    },
    {
        "nurse1": "CT_19",
        "nurse2": "NU_6",
        "cooperation_score": 1.2557448341655502
    },
    {
        "nurse1": "HN_4",
        "nurse2": "NU_6",
        "cooperation_score": 2.0273914022517467
    },
    {
        "nurse1": "NU_11",
        "nurse2": "NU_6",
        "cooperation_score": 1.1973954822790467
    },
    {
        "nurse1": "NU_13",
        "nurse2": "NU_6",
        "cooperation_score": 1.2669748938711787
    },
    {
        "nurse1": "HN_0",
        "nurse2": "NU_6",
        "cooperation_score": 1.8369107013221293
    },
    {
        "nurse1": "CT_28",
        "nurse2": "NU_6",
        "cooperation_score": 1.0627429716826002
    },
    {
        "nurse1": "NU_6",
        "nurse2": "NU_8",
        "cooperation_score": 2.0904989259629856
    },
    {
        "nurse1": "CT_20",
        "nurse2": "NU_6",
        "cooperation_score": 1.3359720802596693
    },
    {
        "nurse1": "NU_6",
        "nurse2": "TR_32",
        "cooperation_score": 1.378587258115122
    },
    {
        "nurse1": "CT_29",
        "nurse2": "NU_6",
        "cooperation_score": 1.242231056061989
    },
    {
        "nurse1": "NU_6",
        "nurse2": "TR_33",
        "cooperation_score": 1.018415982246915
    },
    {
        "nurse1": "NU_6",
        "nurse2": "TR_37",
        "cooperation_score": 1.1249514932951463
    },
    {
        "nurse1": "CT_25",
        "nurse2": "NU_6",
        "cooperation_score": 1.2452563202714637
    },
    {
        "nurse1": "NU_6",
        "nurse2": "TR_36",
        "cooperation_score": 0.8608017827209509
    },
    {
        "nurse1": "HN_5",
        "nurse2": "NU_6",
        "cooperation_score": 1.7376231467714172
    },
    {
        "nurse1": "NU_6",
        "nurse2": "TR_34",
        "cooperation_score": 0.8461333242444429
    },
    {
        "nurse1": "HN_1",
        "nurse2": "NU_6",
        "cooperation_score": 2.186491325152316
    },
    {
        "nurse1": "CT_19",
        "nurse2": "CT_21",
        "cooperation_score": 1.0065367780840926
    },
    {
        "nurse1": "CT_21",
        "nurse2": "HN_4",
        "cooperation_score": 1.317543286830876
    },
    {
        "nurse1": "CT_21",
        "nurse2": "NU_11",
        "cooperation_score": 0.6687358535184622
    },
    {
        "nurse1": "CT_21",
        "nurse2": "NU_13",
        "cooperation_score": 1.0022411483089233
    },
    {
        "nurse1": "CT_21",
        "nurse2": "HN_0",
        "cooperation_score": 0.8873962280073465
    },
    {
        "nurse1": "CT_21",
        "nurse2": "CT_28",
        "cooperation_score": 0.46770901377678875
    },
    {
        "nurse1": "CT_21",
        "nurse2": "NU_8",
        "cooperation_score": 1.1354917283625725
    },
    {
        "nurse1": "CT_20",
        "nurse2": "CT_21",
        "cooperation_score": 0.9847914482505276
    },
    {
        "nurse1": "CT_21",
        "nurse2": "TR_32",
        "cooperation_score": 0.7493699568928402
    },
    {
        "nurse1": "CT_21",
        "nurse2": "CT_29",
        "cooperation_score": 0.6158302939414125
    },
    {
        "nurse1": "CT_21",
        "nurse2": "TR_33",
        "cooperation_score": 0.6635872010013887
    },
    {
        "nurse1": "CT_21",
        "nurse2": "TR_37",
        "cooperation_score": 1.007969119168473
    },
    {
        "nurse1": "CT_21",
        "nurse2": "CT_25",
        "cooperation_score": 0.8864291395402581
    },
    {
        "nurse1": "CT_21",
        "nurse2": "TR_36",
        "cooperation_score": 0.9495525357518895
    },
    {
        "nurse1": "CT_21",
        "nurse2": "HN_5",
        "cooperation_score": 1.0784242789038185
    },
    {
        "nurse1": "CT_21",
        "nurse2": "TR_34",
        "cooperation_score": 0.692606427389036
    },
    {
        "nurse1": "CT_21",
        "nurse2": "HN_1",
        "cooperation_score": 1.2334011576658634
    },
    {
        "nurse1": "CT_19",
        "nurse2": "HN_4",
        "cooperation_score": 1.319392297813014
    },
    {
        "nurse1": "CT_19",
        "nurse2": "NU_11",
        "cooperation_score": 1.2982553536261974
    },
    {
        "nurse1": "CT_19",
        "nurse2": "NU_13",
        "cooperation_score": 1.0540277389113033
    },
    {
        "nurse1": "CT_19",
        "nurse2": "HN_0",
        "cooperation_score": 1.3350615142175242
    },
    {
        "nurse1": "CT_19",
        "nurse2": "CT_28",
        "cooperation_score": 0.8429998778834422
    },
    {
        "nurse1": "CT_19",
        "nurse2": "NU_8",
        "cooperation_score": 1.429284352147456
    },
    {
        "nurse1": "CT_19",
        "nurse2": "CT_20",
        "cooperation_score": 1.2837193177666324
    },
    {
        "nurse1": "CT_19",
        "nurse2": "TR_32",
        "cooperation_score": 0.9954428597381888
    },
    {
        "nurse1": "CT_19",
        "nurse2": "CT_29",
        "cooperation_score": 0.7061580647258396
    },
    {
        "nurse1": "CT_19",
        "nurse2": "TR_33",
        "cooperation_score": 1.06907887135374
    },
    {
        "nurse1": "CT_19",
        "nurse2": "TR_37",
        "cooperation_score": 0.8690007775685524
    },
    {
        "nurse1": "CT_19",
        "nurse2": "CT_25",
        "cooperation_score": 0.9044413174208572
    },
    {
        "nurse1": "CT_19",
        "nurse2": "TR_36",
        "cooperation_score": 0.8384553426113528
    },
    {
        "nurse1": "CT_19",
        "nurse2": "HN_5",
        "cooperation_score": 1.5205776922259624
    },
    {
        "nurse1": "CT_19",
        "nurse2": "TR_34",
        "cooperation_score": 0.7312611335360023
    },
    {
        "nurse1": "CT_19",
        "nurse2": "HN_1",
        "cooperation_score": 1.4980609260021023
    },
    {
        "nurse1": "HN_4",
        "nurse2": "NU_11",
        "cooperation_score": 1.809196181579746
    },
    {
        "nurse1": "HN_4",
        "nurse2": "NU_13",
        "cooperation_score": 1.1455820323467383
    },
    {
        "nurse1": "HN_0",
        "nurse2": "HN_4",
        "cooperation_score": 2.1342352335150827
    },
    {
        "nurse1": "CT_28",
        "nurse2": "HN_4",
        "cooperation_score": 0.8514261452341947
    },
    {
        "nurse1": "HN_4",
        "nurse2": "NU_8",
        "cooperation_score": 2.1043374996699806
    },
    {
        "nurse1": "CT_20",
        "nurse2": "HN_4",
        "cooperation_score": 1.3524510691070795
    },
    {
        "nurse1": "HN_4",
        "nurse2": "TR_32",
        "cooperation_score": 1.4141138660101509
    },
    {
        "nurse1": "CT_29",
        "nurse2": "HN_4",
        "cooperation_score": 1.4337534225843556
    },
    {
        "nurse1": "HN_4",
        "nurse2": "TR_33",
        "cooperation_score": 1.4112481500790828
    },
    {
        "nurse1": "HN_4",
        "nurse2": "TR_37",
        "cooperation_score": 1.2310250980529618
    },
    {
        "nurse1": "CT_25",
        "nurse2": "HN_4",
        "cooperation_score": 1.6721724596876029
    },
    {
        "nurse1": "HN_4",
        "nurse2": "TR_36",
        "cooperation_score": 1.4007729226920909
    },
    {
        "nurse1": "HN_4",
        "nurse2": "HN_5",
        "cooperation_score": 1.96080551995379
    },
    {
        "nurse1": "HN_4",
        "nurse2": "TR_34",
        "cooperation_score": 0.9061659816455213
    },
    {
        "nurse1": "HN_1",
        "nurse2": "HN_4",
        "cooperation_score": 2.6110372470666587
    },
    {
        "nurse1": "NU_11",
        "nurse2": "NU_13",
        "cooperation_score": 1.4395127819040863
    },
    {
        "nurse1": "HN_0",
        "nurse2": "NU_11",
        "cooperation_score": 1.4476271950107595
    },
    {
        "nurse1": "CT_28",
        "nurse2": "NU_11",
        "cooperation_score": 0.7499865186936124
    },
    {
        "nurse1": "NU_11",
        "nurse2": "NU_8",
        "cooperation_score": 1.3569109953700749
    },
    {
        "nurse1": "CT_20",
        "nurse2": "NU_11",
        "cooperation_score": 1.2590935350526142
    },
    {
        "nurse1": "NU_11",
        "nurse2": "TR_32",
        "cooperation_score": 1.2571598407276157
    },
    {
        "nurse1": "CT_29",
        "nurse2": "NU_11",
        "cooperation_score": 0.8297987815941107
    },
    {
        "nurse1": "NU_11",
        "nurse2": "TR_33",
        "cooperation_score": 0.678812764911163
    },
    {
        "nurse1": "NU_11",
        "nurse2": "TR_37",
        "cooperation_score": 1.0258124901078194
    },
    {
        "nurse1": "CT_25",
        "nurse2": "NU_11",
        "cooperation_score": 0.964488683195777
    },
    {
        "nurse1": "NU_11",
        "nurse2": "TR_36",
        "cooperation_score": 0.5744093181164118
    },
    {
        "nurse1": "HN_5",
        "nurse2": "NU_11",
        "cooperation_score": 1.2946580451375846
    },
    {
        "nurse1": "NU_11",
        "nurse2": "TR_34",
        "cooperation_score": 0.8129055726881813
    },
    {
        "nurse1": "HN_1",
        "nurse2": "NU_11",
        "cooperation_score": 1.5238247863247865
    },
    {
        "nurse1": "HN_0",
        "nurse2": "NU_13",
        "cooperation_score": 1.0755973988172132
    },
    {
        "nurse1": "CT_28",
        "nurse2": "NU_13",
        "cooperation_score": 1.1474388599540033
    },
    {
        "nurse1": "NU_13",
        "nurse2": "NU_8",
        "cooperation_score": 1.7811620811772244
    },
    {
        "nurse1": "CT_20",
        "nurse2": "NU_13",
        "cooperation_score": 1.0924231455342641
    },
    {
        "nurse1": "NU_13",
        "nurse2": "TR_32",
        "cooperation_score": 1.2268812313081394
    },
    {
        "nurse1": "CT_29",
        "nurse2": "NU_13",
        "cooperation_score": 0.8588300588300588
    },
    {
        "nurse1": "NU_13",
        "nurse2": "TR_33",
        "cooperation_score": 0.7237978380931671
    },
    {
        "nurse1": "NU_13",
        "nurse2": "TR_37",
        "cooperation_score": 1.047763578235378
    },
    {
        "nurse1": "CT_25",
        "nurse2": "NU_13",
        "cooperation_score": 0.8485698941581294
    },
    {
        "nurse1": "NU_13",
        "nurse2": "TR_36",
        "cooperation_score": 0.493018093018093
    },
    {
        "nurse1": "HN_5",
        "nurse2": "NU_13",
        "cooperation_score": 1.140347457839718
    },
    {
        "nurse1": "NU_13",
        "nurse2": "TR_34",
        "cooperation_score": 0.8622750042019123
    },
    {
        "nurse1": "HN_1",
        "nurse2": "NU_13",
        "cooperation_score": 1.4114817758780605
    },
    {
        "nurse1": "CT_28",
        "nurse2": "HN_0",
        "cooperation_score": 1.1182213383451773
    },
    {
        "nurse1": "HN_0",
        "nurse2": "NU_8",
        "cooperation_score": 1.7959791483549727
    },
    {
        "nurse1": "CT_20",
        "nurse2": "HN_0",
        "cooperation_score": 1.1927971995847888
    },
    {
        "nurse1": "HN_0",
        "nurse2": "TR_32",
        "cooperation_score": 1.395867200395064
    },
    {
        "nurse1": "CT_29",
        "nurse2": "HN_0",
        "cooperation_score": 1.3075759450910884
    },
    {
        "nurse1": "HN_0",
        "nurse2": "TR_33",
        "cooperation_score": 1.2025670650822085
    },
    {
        "nurse1": "HN_0",
        "nurse2": "TR_37",
        "cooperation_score": 1.2188364696878629
    },
    {
        "nurse1": "CT_25",
        "nurse2": "HN_0",
        "cooperation_score": 1.4020033314302398
    },
    {
        "nurse1": "HN_0",
        "nurse2": "TR_36",
        "cooperation_score": 0.6843214218365652
    },
    {
        "nurse1": "HN_0",
        "nurse2": "HN_5",
        "cooperation_score": 1.6461115752675852
    },
    {
        "nurse1": "HN_0",
        "nurse2": "TR_34",
        "cooperation_score": 0.8553833879062712
    },
    {
        "nurse1": "HN_0",
        "nurse2": "HN_1",
        "cooperation_score": 1.6208723852686702
    },
    {
        "nurse1": "CT_28",
        "nurse2": "NU_8",
        "cooperation_score": 1.1027387071656152
    },
    {
        "nurse1": "CT_20",
        "nurse2": "CT_28",
        "cooperation_score": 1.0804775747651638
    },
    {
        "nurse1": "CT_28",
        "nurse2": "TR_32",
        "cooperation_score": 1.1165304709573791
    },
    {
        "nurse1": "CT_28",
        "nurse2": "CT_29",
        "cooperation_score": 0.9096623534704029
    },
    {
        "nurse1": "CT_28",
        "nurse2": "TR_33",
        "cooperation_score": 0.7796732921884356
    },
    {
        "nurse1": "CT_28",
        "nurse2": "TR_37",
        "cooperation_score": 0.8613315032584113
    },
    {
        "nurse1": "CT_25",
        "nurse2": "CT_28",
        "cooperation_score": 0.5685063904104152
    },
    {
        "nurse1": "CT_28",
        "nurse2": "TR_36",
        "cooperation_score": 0.3490128722326865
    },
    {
        "nurse1": "CT_28",
        "nurse2": "HN_5",
        "cooperation_score": 0.9910420848501342
    },
    {
        "nurse1": "CT_28",
        "nurse2": "TR_34",
        "cooperation_score": 0.6994822414091496
    },
    {
        "nurse1": "CT_28",
        "nurse2": "HN_1",
        "cooperation_score": 0.8843931782012276
    },
    {
        "nurse1": "CT_20",
        "nurse2": "NU_8",
        "cooperation_score": 1.5032816568723149
    },
    {
        "nurse1": "NU_8",
        "nurse2": "TR_32",
        "cooperation_score": 1.8705203536237325
    },
    {
        "nurse1": "CT_29",
        "nurse2": "NU_8",
        "cooperation_score": 1.2542234797030192
    },
    {
        "nurse1": "NU_8",
        "nurse2": "TR_33",
        "cooperation_score": 1.2515575038323727
    },
    {
        "nurse1": "NU_8",
        "nurse2": "TR_37",
        "cooperation_score": 0.9367533466369111
    },
    {
        "nurse1": "CT_25",
        "nurse2": "NU_8",
        "cooperation_score": 1.2710164089959486
    },
    {
        "nurse1": "NU_8",
        "nurse2": "TR_36",
        "cooperation_score": 0.7640678020473417
    },
    {
        "nurse1": "HN_5",
        "nurse2": "NU_8",
        "cooperation_score": 1.6908635338353335
    },
    {
        "nurse1": "NU_8",
        "nurse2": "TR_34",
        "cooperation_score": 1.0087581849881622
    },
    {
        "nurse1": "HN_1",
        "nurse2": "NU_8",
        "cooperation_score": 2.0231881250844097
    },
    {
        "nurse1": "CT_20",
        "nurse2": "TR_32",
        "cooperation_score": 1.2875811737805276
    },
    {
        "nurse1": "CT_20",
        "nurse2": "CT_29",
        "cooperation_score": 0.8917367833927936
    },
    {
        "nurse1": "CT_20",
        "nurse2": "TR_33",
        "cooperation_score": 0.8560975114683553
    },
    {
        "nurse1": "CT_20",
        "nurse2": "TR_37",
        "cooperation_score": 0.802615262498827
    },
    {
        "nurse1": "CT_20",
        "nurse2": "CT_25",
        "cooperation_score": 0.9956483130396174
    },
    {
        "nurse1": "CT_20",
        "nurse2": "TR_36",
        "cooperation_score": 0.7718058972854369
    },
    {
        "nurse1": "CT_20",
        "nurse2": "HN_5",
        "cooperation_score": 1.2649853485531235
    },
    {
        "nurse1": "CT_20",
        "nurse2": "TR_34",
        "cooperation_score": 0.8154843234867465
    },
    {
        "nurse1": "CT_20",
        "nurse2": "HN_1",
        "cooperation_score": 1.4451472933671075
    },
    {
        "nurse1": "CT_29",
        "nurse2": "TR_32",
        "cooperation_score": 1.025597398817213
    },
    {
        "nurse1": "TR_32",
        "nurse2": "TR_33",
        "cooperation_score": 1.0358070277339357
    },
    {
        "nurse1": "TR_32",
        "nurse2": "TR_37",
        "cooperation_score": 0.871887613814522
    },
    {
        "nurse1": "CT_25",
        "nurse2": "TR_32",
        "cooperation_score": 1.1156767638965783
    },
    {
        "nurse1": "TR_32",
        "nurse2": "TR_36",
        "cooperation_score": 0.801455854087433
    },
    {
        "nurse1": "HN_5",
        "nurse2": "TR_32",
        "cooperation_score": 1.199377316869577
    },
    {
        "nurse1": "TR_32",
        "nurse2": "TR_34",
        "cooperation_score": 0.7675998264384992
    },
    {
        "nurse1": "HN_1",
        "nurse2": "TR_32",
        "cooperation_score": 1.3103681835879977
    },
    {
        "nurse1": "CT_29",
        "nurse2": "TR_33",
        "cooperation_score": 0.752149895392593
    },
    {
        "nurse1": "CT_29",
        "nurse2": "TR_37",
        "cooperation_score": 0.6315959324473256
    },
    {
        "nurse1": "CT_25",
        "nurse2": "CT_29",
        "cooperation_score": 0.7990156328543055
    },
    {
        "nurse1": "CT_29",
        "nurse2": "TR_36",
        "cooperation_score": 0.8939414371841348
    },
    {
        "nurse1": "CT_29",
        "nurse2": "HN_5",
        "cooperation_score": 1.4522971165924456
    },
    {
        "nurse1": "CT_29",
        "nurse2": "TR_34",
        "cooperation_score": 0.4047007801803198
    },
    {
        "nurse1": "CT_29",
        "nurse2": "HN_1",
        "cooperation_score": 1.2774604480486833
    },
    {
        "nurse1": "TR_33",
        "nurse2": "TR_37",
        "cooperation_score": 0.7665808892353514
    },
    {
        "nurse1": "CT_25",
        "nurse2": "TR_33",
        "cooperation_score": 1.07995177187868
    },
    {
        "nurse1": "TR_33",
        "nurse2": "TR_36",
        "cooperation_score": 0.8017169949596925
    },
    {
        "nurse1": "HN_5",
        "nurse2": "TR_33",
        "cooperation_score": 1.460107666895256
    },
    {
        "nurse1": "TR_33",
        "nurse2": "TR_34",
        "cooperation_score": 0.828906135592769
    },
    {
        "nurse1": "HN_1",
        "nurse2": "TR_33",
        "cooperation_score": 1.1430189091953797
    },
    {
        "nurse1": "CT_25",
        "nurse2": "TR_37",
        "cooperation_score": 0.6038349077822762
    },
    {
        "nurse1": "TR_36",
        "nurse2": "TR_37",
        "cooperation_score": 0.5644390697022276
    },
    {
        "nurse1": "HN_5",
        "nurse2": "TR_37",
        "cooperation_score": 0.632461879365904
    },
    {
        "nurse1": "TR_34",
        "nurse2": "TR_37",
        "cooperation_score": 0.6192190835144127
    },
    {
        "nurse1": "HN_1",
        "nurse2": "TR_37",
        "cooperation_score": 0.8179087854010455
    },
    {
        "nurse1": "CT_25",
        "nurse2": "TR_36",
        "cooperation_score": 0.7833983253252335
    },
    {
        "nurse1": "CT_25",
        "nurse2": "HN_5",
        "cooperation_score": 1.3086763797441547
    },
    {
        "nurse1": "CT_25",
        "nurse2": "TR_34",
        "cooperation_score": 0.5723424522337566
    },
    {
        "nurse1": "CT_25",
        "nurse2": "HN_1",
        "cooperation_score": 1.3895848432613138
    },
    {
        "nurse1": "HN_5",
        "nurse2": "TR_36",
        "cooperation_score": 0.9794606393442038
    },
    {
        "nurse1": "TR_34",
        "nurse2": "TR_36",
        "cooperation_score": 0.08893280632411067
    },
    {
        "nurse1": "HN_1",
        "nurse2": "TR_36",
        "cooperation_score": 1.1519145886792943
    },
    {
        "nurse1": "HN_5",
        "nurse2": "TR_34",
        "cooperation_score": 1.091094838478403
    },
    {
        "nurse1": "HN_1",
        "nurse2": "HN_5",
        "cooperation_score": 2.222989755342697
    },
    {
        "nurse1": "HN_1",
        "nurse2": "TR_34",
        "cooperation_score": 0.5682533539731682
    }
]